forcedimension/__init__.py
forcedimension/dhd/__init__.py
forcedimension/dhd/adaptors.py
forcedimension/dhd/constants.py
forcedimension/dhd/expert.py
forcedimension/dhd/os_independent.py
forcedimension/drd/__init__.py
forcedimension/runtime.py
forcedimension/typing.py
forcedimension/util.py
forcedimension-0.1.7.dist-info/LICENSE
forcedimension-0.1.7.dist-info/METADATA
forcedimension-0.1.7.dist-info/WHEEL
forcedimension-0.1.7.dist-info/RECORD
