Metadata-Version: 2.1
Name: forcedimension
Version: 0.1.7
Summary: Unofficial, Experimental, High-Level Python Wrappers for the Force Dimension SDK
Home-page: https://github.com/EmDash00/forcedimension-python
License: LGPL-3.0
Keywords: forcedimension,haptics,wrappers
Author: Ember Chow
Author-email: emberchow.business@gmail.com
Requires-Python: >=3.8,<3.12
Classifier: Development Status :: 3 - Alpha
Classifier: License :: OSI Approved :: GNU Lesser General Public License v3 (LGPLv3)
Classifier: Operating System :: MacOS :: MacOS X
Classifier: Operating System :: Microsoft :: Windows
Classifier: Operating System :: POSIX :: Linux
Classifier: Programming Language :: Python :: 3
Classifier: Programming Language :: Python :: 3.8
Classifier: Programming Language :: Python :: 3.9
Classifier: Programming Language :: Python :: 3.10
Classifier: Programming Language :: Python :: 3.11
Classifier: Programming Language :: Python :: Implementation :: CPython
Classifier: Topic :: System :: Hardware :: Universal Serial Bus (USB) :: Human Interface Device (HID)
Provides-Extra: numpy
Requires-Dist: numpy (>=1.20,<2.0) ; extra == "numpy"
Project-URL: Documentation, https://forcedimension-python-documentation.readthedocs.io/en/latest/
Project-URL: Repository, https://github.com/EmDash00/forcedimension-python
